<?xml version="1.0" encoding="utf-8"?>
<odoo>

    <record id="sip_call_server_action" model="ir.actions.server">
        <field name="name">Make SIP Call</field>
        <field name="condition">True</field>
        <field name="type">ir.actions.server</field>
        <field name="model_id" ref="model_res_partner" />
        <field name="state">code</field>
        <field name="code">action = env['voip.voip'].start_sip_call(context['active_ids'][0])</field>
    </record>

    <record id="sip_call_more_item" model="ir.values">
        <field eval="'client_action_multi'" name="key2"/>
        <field eval="'res.partner'" name="model"/>
        <field name="name">Make SIP Call</field>
        <field eval="'ir.actions.server,%d'%sip_call_server_action" name="value"/>
    </record>
        
    <record id="view_partner_form_inherit_voip" model="ir.ui.view">
        <field name="name">res.partner Business Directory</field>
        <field name="model">res.partner</field>
        <field name="inherit_id" ref="base.view_partner_form"/>
        <field name="arch" type="xml">
            <field name="mobile" position="after">
                <field name="sip_address"/>
            </field>
      	</field>
    </record>

</odoo>